mapscaler/__init__.py
mapscaler/datasets.py
mapscaler/mapscaler.py
mapscaler/maputils.py
mapscaler/geojson/us_counties.json
mapscaler/geojson/us_states.json
mapscaler-0.0.4.dist-info/LICENSE.txt
mapscaler-0.0.4.dist-info/METADATA
mapscaler-0.0.4.dist-info/WHEEL
mapscaler-0.0.4.dist-info/top_level.txt
mapscaler-0.0.4.dist-info/RECORD
