Metadata-Version: 2.1
Name: mapscaler
Version: 0.0.4
Summary: Scale areas of a geopandas map by any property to create more intuitive and beautiful choropleth visualizations.
Home-page: https://mapscaler.readthedocs.io/en/latest/index.html
Author: Greg Condit
Author-email: conditg@gmail.com
License: gpl-3.0
Download-URL: https://github.com/conditg/mapscaler/archive/v0.0.4.tar.gz
Keywords: DATA VISUALIZATION,MAP,CHOROPLETH,CARTOGRAM,MAP SCALER,GEOJSON
Platform: UNKNOWN
Classifier: Development Status :: 3 - Alpha
Classifier: Intended Audience :: Developers
Classifier: Topic :: Software Development :: Build Tools
Classifier: License :: OSI Approved :: GNU General Public License (GPL)
Classifier: Programming Language :: Python :: 2.6
Classifier: Programming Language :: Python :: 2.7
Classifier: Programming Language :: Python :: 3
Requires-Dist: numpy
Requires-Dist: geopandas
Requires-Dist: shapely
